HNLimits/__init__.py
HNLimits/hnl_tools.py
HNLimits/plot_tools.py
HNLimits/tex_tools.py
HNLimits/Bosonic_CC/__init__.py
HNLimits/Bosonic_CC/bosonic_charged_tools.py
HNLimits/Bosonic_CC/decay_functions.py
HNLimits/Bosonic_CC/plot_tools.py
HNLimits/Bosonic_CC/tex_tools.py
HNLimits/FourFermion_CC/__init__.py
HNLimits/FourFermion_CC/decay_functions.py
HNLimits/FourFermion_CC/fourfermion_charged_tools.py
HNLimits/FourFermion_CC/plot_tools.py
HNLimits/FourFermion_CC/tex_tools.py
HNLimits/include/__init__.py
HNLimits/include/assets/SMEFT-limits-table.tgn
HNLimits/include/assets/logo.png
HNLimits/include/data/1805.08567/FCCee_lower.dat
HNLimits/include/data/1805.08567/FCCee_upper.dat
HNLimits/include/data/1805.08567/Screenshot from 2019-02-18 15-50-46.png
HNLimits/include/data/1805.08567/lower_SHIP.dat
HNLimits/include/data/1805.08567/mathusla_lower.dat
HNLimits/include/data/1805.08567/mathusla_upper.dat
HNLimits/include/data/1805.08567/upper_SHIP.dat
HNLimits/include/data/1805.08567/upper_SHIP.dat#
HNLimits/include/data/1805.08567/wpd_project.tar
HNLimits/include/data/1811.00930/SHIP_Umu4.png
HNLimits/include/data/1811.00930/Umu4_conservative.dat
HNLimits/include/data/1811.00930/Umu4_optimistic.dat
HNLimits/include/data/2101.12304/NA62_2021_mu.dat
HNLimits/include/data/2101.12304/fig6.png
HNLimits/include/data/2101.12304/wpd_project.json
HNLimits/include/data/2205.02234/Utau4_fig2.png
HNLimits/include/data/2205.02234/Utau4_fig2_lower.dat
HNLimits/include/data/2205.02234/Utau4_fig2_upper.dat
HNLimits/include/data/2205.02234/wpd_project.tar
HNLimits/include/data/2306.07315/Ue4_LSND.dat
HNLimits/include/data/2306.07315/Ue4_PIP2BD.dat
HNLimits/include/data/2306.07315/Umu4_LSND.dat
HNLimits/include/data/2306.07315/Umu4_PIP2BD.dat
HNLimits/include/data/ATLAS_2019/Table1.csv
HNLimits/include/data/ATLAS_2019/Table2.csv
HNLimits/include/data/ATLAS_2019/Table3.csv
HNLimits/include/data/ATLAS_2019/Table4.csv
HNLimits/include/data/ATLAS_2019/Table5.csv
HNLimits-1.2.0.dist-info/LICENSE
HNLimits-1.2.0.dist-info/METADATA
HNLimits-1.2.0.dist-info/WHEEL
HNLimits-1.2.0.dist-info/top_level.txt
HNLimits-1.2.0.dist-info/RECORD
