Metadata-Version: 2.1
Name: HNLimits
Version: 1.2.0
Summary: A collection of limits on heavy neutral leptons, including their nuSMEFT interactions
Home-page: https://github.com/mhostert/heavy-neutrino-limits
Author-email: "mhostert@g.harvard.edu"
License: "MIT"
Classifier: Programming Language :: Cython
Classifier: Programming Language :: Python :: 3
Classifier: Programming Language :: Python :: 3.7
Classifier: Programming Language :: Python :: 3.8
Classifier: Programming Language :: Python :: 3.9
Classifier: Programming Language :: Python :: 3.10
Classifier: Programming Language :: Python :: 3.11
Classifier: License :: OSI Approved :: MIT License
Classifier: Operating System :: OS Independent
Classifier: Intended Audience :: Science/Research
Classifier: Topic :: Scientific/Engineering
Requires-Python: >=3.7
License-File: LICENSE
Requires-Dist: numpy
Requires-Dist: scipy
Requires-Dist: pandas>=1.0
Requires-Dist: Particle
Requires-Dist: matplotlib
Requires-Dist: hepunits
Requires-Dist: pylatex
Provides-Extra: testing
Requires-Dist: pytest>=6.0; extra == "testing"
Requires-Dist: pytest-cov>=2.0; extra == "testing"
Requires-Dist: tox>=3.24; extra == "testing"
Requires-Dist: pyarrow; extra == "testing"
